avro/LICENSE
avro/NOTICE
avro/__init__.py
avro/avro_builder.py
avro/constants.py
avro/datafile.py
avro/io.py
avro/ipc.py
avro/protocol.py
avro/schema.py
avro/timezones.py
avro/tool.py
avro/txipc.py
yelp-avro/LICENSE
yelp-avro/NOTICE
yelp-avro/__init__.py
yelp-avro/avro_builder.py
yelp-avro/constants.py
yelp-avro/datafile.py
yelp-avro/io.py
yelp-avro/ipc.py
yelp-avro/protocol.py
yelp-avro/schema.py
yelp-avro/timezones.py
yelp-avro/tool.py
yelp-avro/txipc.py
yelp_avro/LICENSE
yelp_avro/NOTICE
yelp_avro/__init__.py
yelp_avro/avro_builder.py
yelp_avro/constants.py
yelp_avro/datafile.py
yelp_avro/io.py
yelp_avro/ipc.py
yelp_avro/protocol.py
yelp_avro/schema.py
yelp_avro/timezones.py
yelp_avro/tool.py
yelp_avro/txipc.py
yelp_avro-1.9.2.data/scripts/avro
yelp_avro-1.9.2.dist-info/DESCRIPTION.rst
yelp_avro-1.9.2.dist-info/METADATA
yelp_avro-1.9.2.dist-info/RECORD
yelp_avro-1.9.2.dist-info/WHEEL
yelp_avro-1.9.2.dist-info/metadata.json
yelp_avro-1.9.2.dist-info/top_level.txt
